{
  "dataloader": {
    "workers": 7
  },
  "ucf101": {
    "path": "/media/navrudh/Data/ML/dataset",
    "custom-anno-split": "",
    "workers": 7
  },
  "bouncing-balls": {
    "size": 224,
    "n-balls": 3,
    "timesteps": 128
  },
  "workdir": "/media/navrudh/Data/models/vision-classification/bb-2",
  "prediction": {
    "batch_size": 1,
    "trainer_args": {
      "max_epochs": 20,
      "gradient_clip_val": 0.25,
      "accumulate_grad_batches": 2,
      "gpus": 1
    }
  },
  "classification": {
  }
}